sql_builder/__init__.py
sql_builder/sql.py
sql_builder-0.0.25.dist-info/METADATA
sql_builder-0.0.25.dist-info/RECORD
sql_builder-0.0.25.dist-info/WHEEL
sql_builder-0.0.25.dist-info/top_level.txt
