Metadata-Version: 2.1
Name: sql-builder
Version: 0.0.25
Summary: A builder for SQL statement
Home-page: https://github.com/it-allen/sql-builder
Author: Allen Zou
Author-email: zyl_work@163.com
License: MIT
Keywords: sql
Platform: UNKNOWN
Classifier: Development Status :: 4 - Beta
Classifier: Intended Audience :: Developers
Classifier: Topic :: Software Development :: Build Tools
Classifier: License :: OSI Approved :: MIT License
Classifier: Programming Language :: Python :: 2.6
Classifier: Programming Language :: Python :: 2.7
Classifier: Programming Language :: Python :: 3
Classifier: Programming Language :: Python :: 3.3
Classifier: Programming Language :: Python :: 3.4
Classifier: Programming Language :: Python :: 3.5
Classifier: Programming Language :: Python :: 3.6
Requires-Dist: six (>=1.11.0)
